spell_hunter/__init__.py
spell_hunter/spell_hunter.cpython-313-x86_64-linux-gnu.so
spell_hunter-0.1.2.dist-info/METADATA
spell_hunter-0.1.2.dist-info/WHEEL
spell_hunter-0.1.2.dist-info/RECORD
