Metadata-Version: 2.4
Name: spell_hunter
Version: 0.1.2
Classifier: Programming Language :: Rust
Classifier: Programming Language :: Python :: Implementation :: CPython
Classifier: Programming Language :: Python :: Implementation :: PyPy
Summary: Python module for finding interesting bytes in files
Keywords: reverse engineering,rust,files,binaries,forensics,forensic,research,security,binary analysis
Home-Page: https://carefuldata.com
Author-email: Keegan Bowen <carefuldata@protonmail.com>
License: MIT
Requires-Python: >=3.8
Project-URL: Documentation, https://github.com/jpegleg/spell_hunter/README.md
Project-URL: Homepage, https://carefuldata.com
Project-URL: Issues, https://github.com/jpegleg/spell_hunter/issues
Project-URL: Repository, https://github.com/jpegleg/spell_hunter
